notifd/__init__.py
notifd/notifd.py
notifd/notifdctl.py
notifd-0.0.2.dist-info/METADATA
notifd-0.0.2.dist-info/WHEEL
notifd-0.0.2.dist-info/entry_points.txt
notifd-0.0.2.dist-info/licenses/LICENSE
notifd-0.0.2.dist-info/RECORD
