Metadata-Version: 2.1
Name: notifd
Version: 0.0.2
Project-URL: Homepage, https://github.com/rmoretto/notifd
Project-URL: Bug Tracker, https://github.com/rmoretto/notifd/issues
Author-email: Rodrigo Ce Moretto <rodrigo.ce.moretto@gmail.com>
License-File: LICENSE
Classifier: License :: OSI Approved :: MIT License
Classifier: Programming Language :: Python :: 3
Requires-Python: >=3.10
Requires-Dist: click
Requires-Dist: dbus-python
Requires-Dist: pillow
Requires-Dist: pygobject
